ceruleo/__init__.py
ceruleo/dataset/__init__.py
ceruleo/dataset/transformed.py
ceruleo/dataset/ts_dataset.py
ceruleo/dataset/utils.py
ceruleo/dataset/analysis/__init__.py
ceruleo/dataset/analysis/correlation.py
ceruleo/dataset/analysis/distribution.py
ceruleo/dataset/analysis/numerical_features.py
ceruleo/dataset/analysis/sample_rate.py
ceruleo/dataset/builder/__init__.py
ceruleo/dataset/builder/builder.py
ceruleo/dataset/builder/cycles_splitter.py
ceruleo/dataset/builder/output.py
ceruleo/dataset/builder/rul_column.py
ceruleo/dataset/catalog/CMAPSS.py
ceruleo/dataset/catalog/CMAPSS2.py
ceruleo/dataset/catalog/PHMDataset2018.py
ceruleo/dataset/catalog/__init__.py
ceruleo/graphics/__init__.py
ceruleo/graphics/analysis.py
ceruleo/graphics/duration.py
ceruleo/graphics/explanations.py
ceruleo/graphics/results.py
ceruleo/graphics/utils/__init__.py
ceruleo/graphics/utils/curly_brace.py
ceruleo/iterators/__init__.py
ceruleo/iterators/batcher.py
ceruleo/iterators/iterators.py
ceruleo/iterators/sample_weight.py
ceruleo/iterators/shufflers.py
ceruleo/iterators/utils.py
ceruleo/models/__init__.py
ceruleo/models/baseline.py
ceruleo/models/pytorch.py
ceruleo/models/sklearn.py
ceruleo/models/inspection/feature_importance.py
ceruleo/models/keras/__init__.py
ceruleo/models/keras/callbacks.py
ceruleo/models/keras/dataset.py
ceruleo/models/keras/layers.py
ceruleo/models/keras/losses.py
ceruleo/models/keras/weibull.py
ceruleo/models/keras/catalog/CNLSTM.py
ceruleo/models/keras/catalog/InceptionTime.py
ceruleo/models/keras/catalog/MSWRLRCN.py
ceruleo/models/keras/catalog/MVCNN.py
ceruleo/models/keras/catalog/MultiScaleConvolutional.py
ceruleo/models/keras/catalog/MultiTaskRUL.py
ceruleo/models/keras/catalog/XCM.py
ceruleo/models/keras/catalog/XiangQiangJianQiao.py
ceruleo/models/keras/catalog/__init__.py
ceruleo/models/torch/__init__.py
ceruleo/models/torch/dsanet.py
ceruleo/models/torch/model.py
ceruleo/results/__init__.py
ceruleo/results/picewise_regression.py
ceruleo-3.0.6.dist-info/METADATA
ceruleo-3.0.6.dist-info/WHEEL
ceruleo-3.0.6.dist-info/licenses/LICENSE
ceruleo-3.0.6.dist-info/RECORD
