Metadata-Version: 2.3
Name: ceruleo
Version: 3.0.6
Summary: Remaining useful life estimation utilities
Project-URL: Homepage, https://github.com/lucianolorenti/ceruleo
Project-URL: Documentation, https://lucianolorenti.github.io/ceruleo/
License: MIT
License-File: LICENSE
Keywords: predictive maintenance,remaining useful life
Classifier: Programming Language :: Python :: 3
Classifier: Topic :: Scientific/Engineering :: Artificial Intelligence
Requires-Python: >=3.7
Requires-Dist: antropy>=0.1.5
Requires-Dist: emd>=0.4
Requires-Dist: gdown>=4.2
Requires-Dist: mmh3>=2.0
Requires-Dist: numpy>=1.22
Requires-Dist: pandas>=1.5
Requires-Dist: pyarrow>=4
Requires-Dist: pydantic<3.0.0,>=1.0.0
Requires-Dist: pyinform>=0.2
Requires-Dist: pyts>=0.12
Requires-Dist: pywavelets>=1.3
Requires-Dist: scikit-learn>=1.3.2
Requires-Dist: seaborn>=0.11
Requires-Dist: tqdm>=4.56
Requires-Dist: uncertainties>=3.1
Provides-Extra: doc
Requires-Dist: jupyter-contrib-nbextensions; extra == 'doc'
Requires-Dist: mkdocs; extra == 'doc'
Requires-Dist: mkdocs-bibtex; extra == 'doc'
Requires-Dist: mkdocs-jupyter; extra == 'doc'
Requires-Dist: mkdocs-material; extra == 'doc'
Requires-Dist: mkdocs-matplotlib; extra == 'doc'
Requires-Dist: mkdocstrings; extra == 'doc'
Requires-Dist: mkdocstrings[python]; extra == 'doc'
Requires-Dist: notebook<=6.5; extra == 'doc'
Requires-Dist: sphinxcontrib-bibtex; extra == 'doc'
Provides-Extra: tensorflow
Requires-Dist: tensorflow>=2.5; extra == 'tensorflow'
Provides-Extra: test
Requires-Dist: coverage; extra == 'test'
Requires-Dist: nbmake>=1.5.0; extra == 'test'
Requires-Dist: pytest; extra == 'test'
Requires-Dist: xgboost>=1.5; extra == 'test'
